[
  [
    {
      "UUID": [
        "proxiedtaxonnode",
        "9794fc1b-9227-448e-85f2-312dcda1b82d"
      ]
    },
    {
      "PopulationNode": "ProxiedTaxonNode"
    }
  ],
  [
    [
      {
        "UUID": [
          "proxiedtaxonnode",
          "9794fc1b-9227-448e-85f2-312dcda1b82d"
        ]
      },
      {
        "FriendlyKey": [
          "biodiversitydimensionnode",
          "abundance"
        ]
      },
      1,
      {
        "Population": "MeasuredBy"
      }
    ],
    [
      {
        "UUID": [
          "proxiedtaxonnode",
          "9794fc1b-9227-448e-85f2-312dcda1b82d"
        ]
      },
      {
        "FriendlyKey": [
          "taxonnode",
          "genus_chamaenerion"
        ]
      },
      1,
      {
        "Population": "InferredAs"
      }
    ],
    [
      {
        "UUID": [
          "proxiedtaxonnode",
          "9794fc1b-9227-448e-85f2-312dcda1b82d"
        ]
      },
      {
        "FriendlyKey": [
          "inferencemethodnode",
          "atlas_lookup_fshsavhitssaegbggu"
        ]
      },
      1,
      {
        "Population": "InferredUsing"
      }
    ],
    [
      {
        "UUID": [
          "proxiedtaxonnode",
          "9794fc1b-9227-448e-85f2-312dcda1b82d"
        ]
      },
      {
        "FriendlyKey": [
          "bioticproxynode",
          "morphotype_pollen_chamaenerion type"
        ]
      },
      1,
      {
        "Population": "InferredFrom"
      }
    ]
  ]
]