[
  [
    {
      "UUID": [
        "digitiseddatasetnode",
        "2f28a298-3b97-4e2e-adc5-15d29b257f54"
      ]
    },
    {
      "DatasetNode": {
        "Digitised": {
          "WhatWasDigitised": {
            "FromSupplementaryFigure": {
              "item": "Plate 3"
            }
          },
          "SoftwareUsed": "PlotDigitizer",
          "Metric": "Abundance",
          "Units": "PercentAbundance",
          "DigitisedBy": {
            "item1": [
              "L",
              "E"
            ],
            "item2": "Bell"
          },
          "DigitisedOn": {
            "item": "2025-03-24"
          },
          "DataTable": {
            "item": {
              "Index": [
                0.0,
                7.28477,
                11.65563,
                16.02649,
                18.9404,
                23.31126,
                27.68212,
                31.3245,
                34.96689,
                39.33775,
                43.70861,
                48.07947,
                51.72185,
                56.09272,
                59.7351,
                64.10596,
                67.74834,
                72.11921,
                75.76159,
                80.13245,
                84.50331,
                88.87417,
                92.51656,
                96.15894,
                99.07285,
                100.5298
              ],
              "IndexUnit": "Depths",
              "Morphotypes": [
                "Poaceae",
                "Oxyria digyna",
                "Saxifraga oppositifolia type",
                "Cerastium-Stellaria",
                "Papever radicatum",
                "Dryas",
                "Cystopteris fragilis ssp. dickiea",
                "Dryopteris type",
                "Minuartia-Silene",
                "Huperzia selago",
                "Tofieldia",
                "Campanula",
                "Potentilla",
                "Cruciferae",
                "Erigeron-Gnaphalium",
                "Cyperaceae",
                "Empetrum hermaphroditum",
                "Vaccinium type",
                "Cassiope tetragona",
                "Ericales sp. indeterminate",
                "Rhododendron type",
                "Luzula-Juncus",
                "Diapensia lapponica",
                "Salix arctica type",
                "Salix herbacea type"
              ],
              "Data": [
                [
                  12.70588,
                  0.0,
                  0.0,
                  0.0,
                  0.0,
                  0.0,
                  0.0,
                  1.42857,
                  0.0,
                  3.57143,
                  0.0,
                  0.0,
                  0.0,
                  0.0,
                  0.0,
                  21.42857,
                  1.33333,
                  0.0,
                  26.08696,
                  0.71429,
                  0.0,
                  0.71429,
                  0.0,
                  8.29268,
                  11.03448
                ],
                [
                  4.23529,
                  1.22449,
                  0.0,
                  0.0,
                  0.71429,
                  0.0,
                  0.0,
                  0.0,
                  2.14286,
                  4.28571,
                  0.0,
                  0.0,
                  0.0,
                  0.0,
                  0.0,
                  23.57143,
                  2.0,
                  0.0,
                  33.33333,
                  2.85714,
                  0.0,
                  0.0,
                  0.0,
                  8.29268,
                  8.27586
                ],
                [
                  4.94118,
                  1.22449,
                  0.71429,
                  0.0,
                  0.0,
                  0.0,
                  0.0,
                  0.0,
                  0.0,
                  2.85714,
                  0.0,
                  0.0,
                  0.0,
                  0.0,
                  0.0,
                  27.85714,
                  0.66667,
                  0.0,
                  36.23188,
                  0.71429,
                  0.0,
                  0.71429,
                  0.0,
                  4.39024,
                  10.34483
                ],
                [
                  0.70588,
                  1.22449,
                  1.42857,
                  0.0,
                  0.0,
                  0.0,
                  0.0,
                  0.0,
                  0.0,
                  2.85714,
                  0.0,
                  0.0,
                  0.0,
                  0.0,
                  0.0,
                  20.0,
                  0.66667,
                  0.0,
                  36.23188,
                  5.0,
                  0.0,
                  0.71429,
                  0.0,
                  7.80488,
                  11.03448
                ],
                [
                  1.41176,
                  3.67347,
                  0.0,
                  0.0,
                  0.0,
                  0.0,
                  0.0,
                  0.0,
                  0.0,
                  5.71429,
                  0.0,
                  0.0,
                  0.0,
                  0.0,
                  0.0,
                  27.14286,
                  0.0,
                  0.0,
                  34.78261,
                  2.14286,
                  0.0,
                  0.0,
                  0.0,
                  3.90244,
                  11.03448
                ],
                [
                  2.82353,
                  1.83673,
                  0.0,
                  0.71429,
                  0.0,
                  0.71429,
                  0.0,
                  0.71429,
                  0.0,
                  2.14286,
                  0.0,
                  0.0,
                  0.0,
                  0.0,
                  0.0,
                  30.71429,
                  2.0,
                  0.71429,
                  28.26087,
                  1.42857,
                  0.0,
                  0.0,
                  0.0,
                  8.29268,
                  9.65517
                ],
                [
                  2.82353,
                  4.89796,
                  0.0,
                  0.0,
                  0.0,
                  0.0,
                  0.0,
                  0.0,
                  0.71429,
                  4.28571,
                  0.0,
                  0.0,
                  0.0,
                  0.0,
                  0.0,
                  32.14286,
                  0.0,
                  0.0,
                  28.26087,
                  3.57143,
                  0.0,
                  0.0,
                  1.33333,
                  5.85366,
                  6.89655
                ],
                [
                  1.41176,
                  2.44898,
                  0.71429,
                  0.0,
                  0.0,
                  0.71429,
                  0.0,
                  0.0,
                  1.42857,
                  2.85714,
                  0.0,
                  0.0,
                  0.0,
                  0.0,
                  0.0,
                  26.42857,
                  0.66667,
                  1.42857,
                  32.6087,
                  3.57143,
                  0.0,
                  0.71429,
                  0.0,
                  7.80488,
                  8.27586
                ],
                [
                  2.82353,
                  3.06122,
                  0.71429,
                  0.0,
                  0.0,
                  0.0,
                  0.0,
                  0.0,
                  0.0,
                  5.0,
                  0.0,
                  0.0,
                  0.0,
                  0.0,
                  0.0,
                  32.85714,
                  2.66667,
                  0.0,
                  25.36232,
                  2.14286,
                  0.0,
                  0.0,
                  0.66667,
                  6.82927,
                  6.89655
                ],
                [
                  2.11765,
                  3.06122,
                  1.42857,
                  0.0,
                  0.71429,
                  0.0,
                  0.0,
                  0.0,
                  0.71429,
                  4.28571,
                  0.0,
                  0.0,
                  0.0,
                  0.0,
                  0.76923,
                  40.71429,
                  1.33333,
                  0.71429,
                  20.28986,
                  2.14286,
                  0.0,
                  0.0,
                  0.66667,
                  7.31707,
                  8.27586
                ],
                [
                  2.82353,
                  4.89796,
                  0.0,
                  0.71429,
                  0.71429,
                  0.71429,
                  0.0,
                  0.71429,
                  0.0,
                  3.57143,
                  0.0,
                  0.0,
                  0.0,
                  0.0,
                  0.0,
                  37.14286,
                  0.0,
                  0.0,
                  21.73913,
                  2.85714,
                  0.0,
                  0.0,
                  0.0,
                  8.78049,
                  6.2069
                ],
                [
                  1.41176,
                  4.28571,
                  0.0,
                  0.71429,
                  0.0,
                  0.71429,
                  0.0,
                  0.71429,
                  1.42857,
                  2.14286,
                  0.0,
                  0.0,
                  0.0,
                  0.0,
                  0.0,
                  38.57143,
                  3.33333,
                  2.14286,
                  20.28986,
                  3.57143,
                  0.0,
                  0.0,
                  0.0,
                  0.0,
                  8.96552
                ],
                [
                  2.82353,
                  2.44898,
                  0.0,
                  0.0,
                  0.0,
                  0.0,
                  0.0,
                  0.71429,
                  0.71429,
                  4.28571,
                  0.71429,
                  0.0,
                  0.0,
                  0.0,
                  0.0,
                  45.71429,
                  1.33333,
                  0.0,
                  16.66667,
                  1.42857,
                  1.42857,
                  0.0,
                  0.0,
                  7.80488,
                  6.2069
                ],
                [
                  3.52941,
                  2.44898,
                  0.0,
                  0.0,
                  0.0,
                  0.71429,
                  0.0,
                  1.42857,
                  0.71429,
                  3.57143,
                  0.0,
                  0.0,
                  0.0,
                  0.0,
                  0.0,
                  49.28571,
                  2.0,
                  0.71429,
                  0.0,
                  0.0,
                  0.0,
                  0.0,
                  0.0,
                  6.34146,
                  0.0
                ],
                [
                  2.11765,
                  3.06122,
                  0.0,
                  0.0,
                  0.0,
                  0.0,
                  0.0,
                  2.85714,
                  0.0,
                  2.14286,
                  0.71429,
                  0.0,
                  0.0,
                  0.0,
                  0.76923,
                  56.42857,
                  0.66667,
                  0.71429,
                  13.76812,
                  1.42857,
                  0.0,
                  0.0,
                  0.0,
                  4.39024,
                  6.89655
                ],
                [
                  2.82353,
                  5.5102,
                  0.0,
                  0.0,
                  0.0,
                  0.0,
                  0.0,
                  0.71429,
                  0.0,
                  3.57143,
                  1.42857,
                  0.0,
                  0.0,
                  0.0,
                  0.0,
                  48.57143,
                  0.66667,
                  2.14286,
                  11.5942,
                  2.14286,
                  0.0,
                  0.0,
                  0.0,
                  4.39024,
                  11.72414
                ],
                [
                  1.41176,
                  4.89796,
                  1.42857,
                  0.0,
                  0.0,
                  0.71429,
                  1.33333,
                  0.71429,
                  0.0,
                  3.57143,
                  0.71429,
                  0.0,
                  0.0,
                  0.0,
                  0.0,
                  52.85714,
                  0.66667,
                  0.0,
                  9.42029,
                  1.42857,
                  0.0,
                  0.0,
                  0.0,
                  6.82927,
                  8.96552
                ],
                [
                  1.41176,
                  3.67347,
                  0.0,
                  0.0,
                  0.0,
                  0.0,
                  0.0,
                  2.14286,
                  0.71429,
                  3.57143,
                  0.0,
                  0.0,
                  0.0,
                  0.0,
                  0.0,
                  55.0,
                  0.66667,
                  0.0,
                  11.5942,
                  1.42857,
                  0.0,
                  0.0,
                  0.0,
                  4.39024,
                  6.89655
                ],
                [
                  2.11765,
                  7.34694,
                  0.0,
                  0.0,
                  0.0,
                  0.0,
                  0.66667,
                  3.57143,
                  1.42857,
                  4.28571,
                  0.0,
                  1.33333,
                  0.0,
                  0.71429,
                  0.76923,
                  45.71429,
                  2.66667,
                  1.42857,
                  14.49275,
                  2.14286,
                  0.0,
                  0.0,
                  0.0,
                  6.82927,
                  4.82759
                ],
                [
                  4.23529,
                  9.79592,
                  0.0,
                  0.0,
                  0.0,
                  0.0,
                  0.0,
                  1.42857,
                  0.0,
                  7.14286,
                  0.0,
                  0.0,
                  0.0,
                  0.0,
                  0.0,
                  36.42857,
                  2.0,
                  0.0,
                  24.63768,
                  2.14286,
                  0.0,
                  0.0,
                  0.0,
                  2.92683,
                  4.82759
                ],
                [
                  6.35294,
                  18.36735,
                  2.14286,
                  0.71429,
                  1.42857,
                  0.0,
                  0.0,
                  3.57143,
                  4.28571,
                  7.14286,
                  0.0,
                  0.0,
                  0.0,
                  0.0,
                  0.0,
                  22.14286,
                  2.66667,
                  0.71429,
                  23.18841,
                  2.85714,
                  0.0,
                  0.0,
                  0.0,
                  0.0,
                  0.0
                ],
                [
                  6.35294,
                  22.65306,
                  2.14286,
                  0.0,
                  0.0,
                  0.0,
                  0.0,
                  0.0,
                  2.85714,
                  7.85714,
                  0.0,
                  0.0,
                  3.57143,
                  0.0,
                  0.0,
                  13.57143,
                  0.0,
                  0.0,
                  15.94203,
                  0.71429,
                  0.0,
                  0.0,
                  0.0,
                  0.0,
                  0.0
                ],
                [
                  10.58824,
                  26.93878,
                  0.0,
                  0.0,
                  2.14286,
                  0.0,
                  0.0,
                  5.71429,
                  10.71429,
                  6.42857,
                  1.42857,
                  0.0,
                  3.57143,
                  0.0,
                  0.0,
                  12.85714,
                  6.0,
                  1.42857,
                  0.0,
                  0.0,
                  0.0,
                  0.0,
                  0.0,
                  0.0,
                  0.0
                ],
                [
                  26.82353,
                  11.63265,
                  0.0,
                  0.0,
                  2.14286,
                  0.0,
                  2.66667,
                  14.28571,
                  7.14286,
                  12.85714,
                  0.0,
                  0.0,
                  0.0,
                  0.0,
                  0.0,
                  15.71429,
                  0.0,
                  0.0,
                  0.0,
                  0.0,
                  0.0,
                  2.14286,
                  0.0,
                  0.0,
                  0.0
                ],
                [
                  39.52941,
                  15.91837,
                  3.57143,
                  0.0,
                  0.0,
                  0.0,
                  0.0,
                  5.0,
                  0.0,
                  7.85714,
                  0.0,
                  0.0,
                  0.0,
                  0.0,
                  0.0,
                  12.85714,
                  0.0,
                  0.0,
                  0.0,
                  0.0,
                  0.0,
                  0.0,
                  0.0,
                  0.0,
                  0.0
                ],
                [
                  48.0,
                  7.34694,
                  0.0,
                  0.0,
                  0.0,
                  0.0,
                  0.0,
                  8.57143,
                  0.0,
                  0.0,
                  0.0,
                  0.0,
                  0.0,
                  0.0,
                  0.0,
                  0.0,
                  0.0,
                  0.0,
                  0.0,
                  0.0,
                  0.0,
                  2.14286,
                  0.0,
                  0.0,
                  0.0
                ]
              ]
            }
          },
          "Dimensions": {
            "item": {
              "Index": [
                0.0,
                7.28477,
                11.65563,
                16.02649,
                18.9404,
                23.31126,
                27.68212,
                31.3245,
                34.96689,
                39.33775,
                43.70861,
                48.07947,
                51.72185,
                56.09272,
                59.7351,
                64.10596,
                67.74834,
                72.11921,
                75.76159,
                80.13245,
                84.50331,
                88.87417,
                92.51656,
                96.15894,
                99.07285,
                100.5298
              ],
              "IndexUnit": "Depths",
              "Morphotypes": [
                "dimension: pollen sum"
              ],
              "Data": [
                [
                  208.0
                ],
                [
                  2016.0
                ],
                [
                  238.0
                ],
                [
                  204.0
                ],
                [
                  305.0
                ],
                [
                  347.0
                ],
                [
                  326.0
                ],
                [
                  332.0
                ],
                [
                  282.0
                ],
                [
                  334.0
                ],
                [
                  286.0
                ],
                [
                  333.0
                ],
                [
                  328.0
                ],
                [
                  302.0
                ],
                [
                  301.0
                ],
                [
                  395.0
                ],
                [
                  334.0
                ],
                [
                  347.0
                ],
                [
                  338.0
                ],
                [
                  199.0
                ],
                [
                  242.0
                ],
                [
                  189.0
                ],
                [
                  114.0
                ],
                [
                  115.0
                ],
                [
                  110.0
                ],
                [
                  115.0
                ]
              ]
            }
          }
        }
      }
    }
  ],
  [
    [
      {
        "UUID": [
          "digitiseddatasetnode",
          "2f28a298-3b97-4e2e-adc5-15d29b257f54"
        ]
      },
      {
        "FriendlyKey": [
          "bioticproxycategorynode",
          "fossilmicro_pollen"
        ]
      },
      1,
      {
        "Dataset": "IsProxyGroup"
      }
    ]
  ]
]