[
  [
    {
      "FriendlyKey": [
        "taxonnode",
        "genus_diapensia"
      ]
    },
    {
      "PopulationNode": {
        "TaxonomyNode": {
          "Genus": {
            "item": "Diapensia"
          }
        }
      }
    }
  ],
  [
    [
      {
        "FriendlyKey": [
          "taxonnode",
          "genus_diapensia"
        ]
      },
      {
        "FriendlyKey": [
          "taxonomicnamesindexnode",
          "nomenclature-index_world flora online"
        ]
      },
      1,
      {
        "Population": {
          "HasIdentifier": {
            "item": "wfo-4000011321"
          }
        }
      }
    ],
    [
      {
        "FriendlyKey": [
          "taxonnode",
          "genus_diapensia"
        ]
      },
      {
        "FriendlyKey": [
          "taxonnode",
          "family_diapensiaceae"
        ]
      },
      1,
      {
        "Population": "IsA"
      }
    ]
  ]
]