[
  [
    {
      "FriendlyKey": [
        "taxonnode",
        "order_saxifragales"
      ]
    },
    {
      "PopulationNode": {
        "TaxonomyNode": {
          "Order": {
            "item": "Saxifragales"
          }
        }
      }
    }
  ],
  [
    [
      {
        "FriendlyKey": [
          "taxonnode",
          "order_saxifragales"
        ]
      },
      {
        "FriendlyKey": [
          "taxonomicnamesindexnode",
          "nomenclature-index_world flora online"
        ]
      },
      1,
      {
        "Population": {
          "HasIdentifier": {
            "item": "wfo-9000000481"
          }
        }
      }
    ],
    [
      {
        "FriendlyKey": [
          "taxonnode",
          "order_saxifragales"
        ]
      },
      {
        "FriendlyKey": [
          "taxonnode",
          "phylum_angiosperms"
        ]
      },
      1,
      {
        "Population": "IsA"
      }
    ]
  ]
]