[
  [
    {
      "FriendlyKey": [
        "taxonnode",
        "species_papaver_radicatum_rottb"
      ]
    },
    {
      "PopulationNode": {
        "TaxonomyNode": {
          "Species": [
            {
              "item": "Papaver"
            },
            {
              "item": "radicatum"
            },
            {
              "item": "Rottb."
            }
          ]
        }
      }
    }
  ],
  [
    [
      {
        "FriendlyKey": [
          "taxonnode",
          "species_papaver_radicatum_rottb"
        ]
      },
      {
        "FriendlyKey": [
          "taxonnode",
          "species_oreomecon_radicata_rottb banfi bartolucci j-mtison amp galasso"
        ]
      },
      1,
      {
        "Population": {
          "IsSynonymOf": [
            {
              "item": "World Flora Online"
            },
            {
              "item": "2024-12-01"
            }
          ]
        }
      }
    ],
    [
      {
        "FriendlyKey": [
          "taxonnode",
          "species_papaver_radicatum_rottb"
        ]
      },
      {
        "FriendlyKey": [
          "taxonomicnamesindexnode",
          "nomenclature-index_world flora online"
        ]
      },
      1,
      {
        "Population": {
          "HasIdentifier": {
            "item": "wfo-0000481007"
          }
        }
      }
    ],
    [
      {
        "FriendlyKey": [
          "taxonnode",
          "species_papaver_radicatum_rottb"
        ]
      },
      {
        "FriendlyKey": [
          "taxonnode",
          "genus_papaver"
        ]
      },
      1,
      {
        "Population": "IsA"
      }
    ]
  ]
]