[
  [
    {
      "FriendlyKey": [
        "taxonnode",
        "subfamily_cryptogrammoideae"
      ]
    },
    {
      "PopulationNode": {
        "TaxonomyNode": {
          "Subfamily": {
            "item": "Cryptogrammoideae"
          }
        }
      }
    }
  ],
  [
    [
      {
        "FriendlyKey": [
          "taxonnode",
          "subfamily_cryptogrammoideae"
        ]
      },
      {
        "FriendlyKey": [
          "taxonomicnamesindexnode",
          "nomenclature-index_world flora online"
        ]
      },
      1,
      {
        "Population": {
          "HasIdentifier": {
            "item": "wfo-6500000505"
          }
        }
      }
    ],
    [
      {
        "FriendlyKey": [
          "taxonnode",
          "subfamily_cryptogrammoideae"
        ]
      },
      {
        "FriendlyKey": [
          "taxonnode",
          "family_pteridaceae"
        ]
      },
      1,
      {
        "Population": "IsA"
      }
    ]
  ]
]